caicollect/__init__.py
caicollect/collect/__init__.py
caicollect/collect/my_class.py
caicollect-1.0.4.dist-info/METADATA
caicollect-1.0.4.dist-info/WHEEL
caicollect-1.0.4.dist-info/top_level.txt
caicollect-1.0.4.dist-info/RECORD
