Metadata-Version: 2.1
Name: caicollect
Version: 1.0.4
Summary: 测试模块
Home-page: UNKNOWN
Author: cai
Author-email: UNKNOWN
License: UNKNOWN
Platform: UNKNOWN
